{
    "success": true,
    "data": {
        "hotList": [{
                "id": 1,
                "title": "为什么经常听说物种灭绝， 却很少听说有新物种诞生？",
                "imgUrl": "https://pic4.zhimg.com/80/v2-b9f9581462a45693574a02bbbcdde264_1440w.jpg?source=1940ef5c",
                "heat": 126
            },
            {
                "id": 2,
                "title": "你永远不会脱粉的明星是谁？",
                "content": "团体，个人都可以！",
                "imgUrl": "https://pic1.zhimg.com/80/v2-07d38ab431240a19758e34eae97236e5_1440w.jpg?source=1940ef5c",
                "heat": 119
            },
            {
                "id": 3,
                "title": "jackeylove 为什么报价那么贵？",
                "heat": 114
            },
            {
                "id": 4,
                "title": "男生喜欢女生的表现是什么？",
                "content": "不知道一个关系不错的男生是否喜欢自己。",
                "heat": 108
            },
            {
                "id": 5,
                "title": "如何看待美日发表探月合作宣言， 日本宇航员将首次登月？",
                "content": "据日本《产经新闻》报道，美日两国政府10日发表了有关探月合作的共同宣言，其中包括了允许日本宇航员首次登月的内容。登陆预计将在2020年代的后半段实现...",
                "heat": 101
            },
            {
                "id": 6,
                "title": "你愿意和重度抑郁的人做朋友吗？",
                "imgUrl": "https://pic1.zhimg.com/80/v2-a55ff2de00d148ccd2e6e868fec5a92c_1440w.jpg?source=1940ef5c",
                "heat": 93
            },
            {
                "id": 7,
                "title": "如何看待吉尔吉斯斯坦单日新增 40 例肺炎死亡病例， 且新冠病毒检测均为阴性？",
                "content": "据该国新闻网站“24.kg”，吉尔吉斯斯坦卫生部公共卫生...",
                "imgUrl": "https://pic2.zhimg.com/80/v2-b2175e321b1152b881a052f62b572f33_1440w.jpg?source=1940ef5c",
                "heat": 88
            },
            {
                "id": 8,
                "title": "全国卷高考基本结束了， 其他国家高考是啥样的？ 有多「 硬核」？",
                "content": "决定命运的全国卷高考基本结束了，又一批年轻人走出了象...",
                "imgUrl": "https://pic2.zhimg.com/80/v2-c52d3500de36d8c59734736ba2e9ef3e_1440w.jpg?source=1940ef5c",
                "heat": 80
            },
            {
                "id": 9,
                "title": "如何看待 2021 年我国独居成年人接近 1 亿？ 大家选择独居的主要原因是什么？",
                "content": "根据民政部的数据显示，2018年我国单身成年人口高达2.4亿人，其中超过7700万成年人...",
                "heat": 77
            },
            {
                "id": 10,
                "title": "如果你是古代的将军， 一次出征打仗， 行军途中， 一阵大风吹折了帅旗， 此时你该怎么办？",
                "imgUrl": "https://pic2.zhimg.com/80/v2-3f028a7d9be961097c69453d57c73e2b_1440w.jpg?source=1940ef5c",
                "heat": 59
            }
        ]
    }
}